fastdimr/__init__.py
fastdimr/__version__.py
fastdimr/wrap.py
fastdimr-0.1.0.dist-info/LICENSE
fastdimr-0.1.0.dist-info/METADATA
fastdimr-0.1.0.dist-info/WHEEL
fastdimr-0.1.0.dist-info/top_level.txt
fastdimr-0.1.0.dist-info/RECORD
