Metadata-Version: 2.1
Name: fastdimr
Version: 0.1.0
Summary: fastdimr - fast dimensionality reduction wrapper.
Home-page: https://github.com/inoueakimitsu/fastdimr
Author: Akimitsu Inoue
Author-email: akimitsu.inoue@gmail.com
License: MIT
Keywords: machine learning
Classifier: Development Status :: 4 - Beta
Classifier: Intended Audience :: Developers
Requires-Python: >=3.7
License-File: LICENSE
Requires-Dist: numpy
Requires-Dist: pandas
Requires-Dist: scikit-learn
